mylib/__init__.py
Group_45-1.1.dist-info/METADATA
Group_45-1.1.dist-info/WHEEL
Group_45-1.1.dist-info/top_level.txt
Group_45-1.1.dist-info/RECORD
