Metadata-Version: 2.1
Name: Group-45
Version: 1.1
Summary: ENSF 338 Final Project
Author: Aser-Ghobara
Author-email: aser.ghobara@ucalgary.ca
Requires-Dist: pytest
